{
	"id": "549.39",
	"url": "https://www.revisor.mn.gov/statutes/cite/549.39",
	"title": "549.39 EFFECTS OF TRANSFER OF STRUCTURED SETTLEMENT PAYMENT RIGHTS.",
	"text": "Following a transfer of structured settlement payment rights:\n(1) the structured settlement obligor and the annuity issuer may rely on the court order approving the transfer in redirecting periodic payments to an assignee or transferee in accordance with the order approving the transfer and shall, as to all parties except the transferee or an assignee designated by the transferee, be discharged and released from any and all liability for the redirected payments and such discharge and release shall not be affected by the failure of any party to the transfer to comply with this chapter or with the court order approving the transfer;\n(2) the transferee is liable to the structured settlement obligor and the annuity issuer:\n(i) if the transfer contravenes the terms of the structured settlement, for any taxes incurred by the structured settlement obligor or annuity issuer as a consequence of the transfer; and\n(ii) for any other liabilities or costs, including reasonable costs and attorney fees, arising from compliance by the structured settlement obligor or annuity issuer with the court order or order of the responsible administrative authority approving the transfer or from the failure of any party to the transfer to comply with sections 549.30 to 549.41;\n(3) neither the annuity issuer nor the structured settlement obligor may be required to divide any periodic payment between the payee and any transferee or assignee or between two or more transferees or assignees; and\n(4) any further transfer of structured settlement payment rights by the payee may be made only after compliance with all of the requirements of sections 549.30 to 549.41.",
	"repealed": false
}