{
	"id": "179A.22",
	"url": "https://www.revisor.mn.gov/statutes/cite/179A.22",
	"title": "179A.22 STATE AND ITS EMPLOYEES; NEGOTIATIONS.",
	"text": "For purposes of this section the term \"appointing authority\" has the meaning given it by section 43A.02, subdivision 5.\nThe employer of state executive branch employees shall be, for purposes of sections 179A.01 to 179A.25, the commissioner of management and budget or the commissioner's representative.\nIn all negotiations between the executive branch of the state and exclusive representatives, the state executive branch shall be represented by the commissioner of management and budget or the commissioner's representative. The attorney general, and each appointing authority shall cooperate with the commissioner of management and budget in conducting negotiations and shall make available any personnel and other resources necessary to enable the commissioner to conduct effective negotiations.\nThe commissioner of management and budget is authorized to enter into agreements with exclusive representatives as provided in section 43A.06, subdivisions 1, paragraph (b), and 3. The Board of Trustees of the Minnesota State Colleges and Universities is authorized to enter into agreements with exclusive representatives as provided in section 43A.06, subdivision 1, paragraph (c). The negotiated agreements and any related arbitration decisions must be implemented by the commissioner of management and budget or the Board of Trustees of the Minnesota State Colleges and Universities respectively, following the approval of the tentative agreement by exclusive representatives.",
	"repealed": false
}