{
	"id": "38.19",
	"url": "https://www.revisor.mn.gov/statutes/cite/38.19",
	"title": "38.19 EXPENDITURE OF APPROPRIATIONS.",
	"text": "The county board owning any such fairground may expend the funds so appropriated and paid over by any such town, statutory city, or school district for the use of the county, in the same manner as the funds of the county set apart for these purposes may be expended; and may, by resolution, set apart for the use of the town, statutory city, or school district any building, or any portion of the fairground, that may be constructed or otherwise improved with the funds so appropriated and paid over to the county by the town, statutory city, or school district, but the title to the building, or other improvement, shall be and remain the property of the county as part of the fairground property.",
	"repealed": false
}