{
	"id": "92.23",
	"url": "https://www.revisor.mn.gov/statutes/cite/92.23",
	"title": "92.23 PAYMENTS; RECEIPTS.",
	"text": "The holder of a certificate of sale may pay the commissioner any amount due on the certificate. The commissioner shall issue duplicate receipts specifying the date, the name and address of the person making the payment, the amount paid, whether for principal or interest, the fund to which it is applicable, and the number of the certificate. The receipt has the same effect as if given by the commissioner of management and budget. The commissioner shall deliver one copy to the holder of the certificate and retain one copy.",
	"repealed": false
}