{
	"id": "642.07",
	"url": "https://www.revisor.mn.gov/statutes/cite/642.07",
	"title": "642.07 CHIEF OF POLICE; DUTIES.",
	"text": "The chief of police shall cause every lockup under the chief's care, and the bedding therein, to be kept clean, wholesome, and free from vermin. The lockup shall be kept in good repair and maintained so as to protect the health, comfort, safety, and well-being of inmates and staff. Each chief of police shall keep a permanent record of all persons committed to the lockup, and all persons admitted as lodgers therein, in the form prescribed by the commissioner of corrections. Any peace officer placing a person in the lockup shall report immediately to the officer's superior concerning the fact of the placement.",
	"repealed": false
}