{
	"id": "116.9403",
	"url": "https://www.revisor.mn.gov/statutes/cite/116.9403",
	"title": "116.9403 IDENTIFYING PRIORITY CHEMICALS.",
	"text": "(a) The department, after consultation with the agency, may designate a chemical of high concern as a priority chemical if the department finds that the chemical:\n(1) has been identified as a high-production volume chemical by the United States Environmental Protection Agency; and\n(2) meets any of the following criteria:\n(i) the chemical has been found through biomonitoring to be present in human blood, including umbilical cord blood, breast milk, urine, or other bodily tissues or fluids;\n(ii) the chemical has been found through sampling and analysis to be present in household dust, indoor air, drinking water, or elsewhere in the home environment; or\n(iii) the chemical has been found through monitoring to be present in fish, wildlife, or the natural environment.\n(b) By February 1, 2011, the department shall publish a list of priority chemicals in the State Register and on the department's Internet website and shall update the published list whenever a new priority chemical is designated.",
	"repealed": false
}