{
	"id": "193.141",
	"url": "https://www.revisor.mn.gov/statutes/cite/193.141",
	"title": "193.141 CONSTRUCTION OF ARMORIES.",
	"text": "In any county or municipality of this state in which there shall at the time be stationed one or more units of the National Guard, and in which the adjutant general shall deem it necessary or expedient to construct an armory, an armory may be constructed and the cost thereof paid as hereinafter provided.\nWhenever the adjutant general shall deem it necessary or expedient that an armory be constructed upon a state military camping ground, to be used principally by any unit or units of the National Guard stationed at a municipality in the vicinity thereof, such armory may be constructed and the cost thereof paid in the manner hereinafter provided for the construction of armories in municipalities.",
	"repealed": false
}