{
	"id": "156.20",
	"url": "https://www.revisor.mn.gov/statutes/cite/156.20",
	"title": "156.20 INSPECTIONS AND SAMPLES.",
	"text": "To enforce sections 156.16 to 156.19, a veterinarian must allow authorized representatives of the Board of Veterinary Medicine, after receiving allegations of a violation of sections 156.16 to 156.19 and upon presenting appropriate credentials to the veterinarian in charge, to:\n(1) enter premises in which veterinary drugs are held for distribution in Minnesota at reasonable times, within reasonable limits, and in a reasonable manner;\n(2) inspect pertinent records, equipment, materials, containers, and facilities bearing on whether veterinary drugs are in compliance with sections 156.16 to 156.19; and\n(3) collect samples.\nAn inspection authorized by this section may not extend to financial information, pricing information, personnel information, or sales information other than shipment information. An inspection must be started and completed with reasonable promptness.",
	"repealed": false
}