{
	"id": "302A.453",
	"url": "https://www.revisor.mn.gov/statutes/cite/302A.453",
	"title": "302A.453 VOTING TRUSTS.",
	"text": "Shares in a corporation may be transferred to a trustee pursuant to written agreement, for the purpose of conferring on the trustee the right to vote and otherwise represent the beneficial owner of those shares for a period not exceeding 15 years, except that if the agreement is made in connection with an indebtedness of the corporation, the voting trust may extend until the indebtedness is discharged. Unless otherwise specified in the agreement, the voting trust may be terminated at any time by the beneficial owners of a majority of the voting power of the shares held by the trustee. A copy of the agreement shall be filed with the corporation.\nUnless otherwise provided in the trust agreement, if there are two or more trustees, the manner of voting is determined as provided in section 302A.445, subdivision 5.",
	"repealed": false
}