{
	"id": "336.3-601",
	"url": "https://www.revisor.mn.gov/statutes/cite/336.3-601",
	"title": "336.3-601 DISCHARGE AND EFFECT OF DISCHARGE.",
	"text": "(a) The obligation of a party to pay the instrument is discharged as stated in this article or by an act or agreement with the party which would discharge an obligation to pay money under a simple contract.\n(b) Discharge of the obligation of a party is not effective against a person acquiring rights of a holder in due course of the instrument without notice of the discharge.",
	"repealed": false
}