{
	"id": "116J.82",
	"url": "https://www.revisor.mn.gov/statutes/cite/116J.82",
	"title": "116J.82 CONSOLIDATED HEARINGS.",
	"text": "The bureau may request the Office of Administrative Hearings to consolidate hearings insofar as it is feasible and agreeable to all parties.\nA consolidated hearing shall be conducted in a manner consistent with sections 14.001 to 14.69, and the applicable rules of the Office of Administrative Hearings.\nThe Office of Administrative Hearings, with the consent of the agencies having license jurisdiction, may provide for a prehearing conference to assist in the disposition of the type, time, place, and parties of the consolidated hearing, the simplification of the issues, the stipulations as to agreed facts and necessary documents, and other relevant matters.",
	"repealed": false
}