{
	"id": "527.39",
	"url": "https://www.revisor.mn.gov/statutes/cite/527.39",
	"title": "527.39 ACCOUNTING BY AND DETERMINATION OF LIABILITY OF CUSTODIAN.",
	"text": "(a) A minor who has attained the age of 14 years, the minor's guardian or legal representative, an adult member of the minor's family, a transferor, or a transferor's legal representative may petition the court (i) for an accounting by the custodian or the custodian's legal representative; or (ii) for a determination of responsibility, as between the custodial property and the custodian personally, for claims against the custodial property unless the responsibility has been adjudicated in an action under section 527.37 to which the minor or the minor's legal representative was a party.\n(b) A successor custodian may petition the court for an accounting by the predecessor custodian.\n(c) The court, in a proceeding under this chapter or in any other proceeding, may require or permit the custodian or the custodian's legal representative to account.\n(d) If a custodian is removed under section 527.38, paragraph (f), the court shall require an accounting and order delivery of the custodial property and records to the successor custodian and the execution of all instruments required for transfer of the custodial property.",
	"repealed": false
}