{
	"id": "123B.571",
	"url": "https://www.revisor.mn.gov/statutes/cite/123B.571",
	"title": "123B.571 RADON TESTING.",
	"text": "The commissioners of health and education may jointly develop a plan to encourage school districts to accurately and efficiently test for the presence of radon in public school buildings serving students in kindergarten through grade 12. To the extent possible, the commissioners shall base the plan on the standards established by the United States Environmental Protection Agency.\nA school district may include radon testing as a part of its ten-year facility plan under section 123B.595, subdivision 4. If a school district receives authority to use long-term facilities maintenance revenue to conduct radon testing, the district shall conduct the testing according to the radon testing plan developed by the commissioners of health and education.\nA school district that has tested its school buildings for the presence of radon shall report the results of its tests to the Department of Health in a form and manner prescribed by the commissioner of health. A school district that has tested for the presence of radon shall also report the results of its testing at a school board meeting.",
	"repealed": false
}