{
	"id": "18D.302",
	"url": "https://www.revisor.mn.gov/statutes/cite/18D.302",
	"title": "18D.302 FALSE STATEMENT OR RECORD.",
	"text": "A person must not knowingly make or offer a false statement, record, or other information as part of:\n(1) an application for registration, license, certification, permit, or land application of contaminated soil or other media under this chapter or chapter 18B, 18C, or 18F or rules adopted under one of those chapters;\n(2) records or reports required under this chapter or chapter 18B, 18C, 18E, or 18F or rules adopted under one of those chapters; or\n(3) an investigation of a violation of this chapter or chapter 18B, 18C, 18E, or 18F or rules adopted under one of those chapters.",
	"repealed": false
}